agent/__init__.py
agent/cli.py
agent/core.py
agent/evening_review.py
agent/models.py
agent/morning_brief.py
agent/plan_manager.py
agent/planner.py
agent/research.py
agent/tasks.py
agent/weekly_review.py
bizy_ai-1.1.1.dist-info/licenses/LICENSE
scripts/init_db.py
scripts/load_business_plan.py
scripts/migrate_db.py
scripts/scheduler.py
bizy_ai-1.1.1.dist-info/METADATA
bizy_ai-1.1.1.dist-info/WHEEL
bizy_ai-1.1.1.dist-info/entry_points.txt
bizy_ai-1.1.1.dist-info/top_level.txt
bizy_ai-1.1.1.dist-info/RECORD
