Metadata-Version: 2.4
Name: bizy-ai
Version: 1.1.1
Summary: AI-powered business planning and execution agent
Author: Reid Chatham
License: MIT
Project-URL: Homepage, https://github.com/reidchatham/bizy-ai
Project-URL: Documentation, https://github.com/reidchatham/bizy-ai#readme
Project-URL: Repository, https://github.com/reidchatham/bizy-ai
Project-URL: Issues, https://github.com/reidchatham/bizy-ai/issues
Keywords: ai,business,planning,productivity,cli,agent
Classifier: Development Status :: 4 - Beta
Classifier: Intended Audience :: Developers
Classifier: Intended Audience :: End Users/Desktop
Classifier: Topic :: Office/Business
Classifier: Topic :: Office/Business :: Scheduling
Classifier: License :: OSI Approved :: MIT License
Classifier: Programming Language :: Python :: 3
Classifier: Programming Language :: Python :: 3.8
Classifier: Programming Language :: Python :: 3.9
Classifier: Programming Language :: Python :: 3.10
Classifier: Programming Language :: Python :: 3.11
Classifier: Programming Language :: Python :: 3.12
Classifier: Programming Language :: Python :: 3.13
Requires-Python: >=3.8
License-File: LICENSE
Requires-Dist: anthropic>=0.18.0
Requires-Dist: schedule>=1.2.0
Requires-Dist: python-dotenv>=1.0.0
Requires-Dist: pyyaml>=6.0
Requires-Dist: sqlalchemy>=2.0.0
Requires-Dist: requests>=2.31.0
Requires-Dist: beautifulsoup4>=4.12.0
Requires-Dist: pandas>=2.0.0
Requires-Dist: rich>=13.0.0
Requires-Dist: python-dateutil>=2.8.2
Requires-Dist: click>=8.1.0
Requires-Dist: jinja2>=3.1.2
Provides-Extra: dev
Requires-Dist: pytest>=7.4.0; extra == "dev"
Requires-Dist: pytest-cov>=4.1.0; extra == "dev"
Requires-Dist: pytest-mock>=3.12.0; extra == "dev"
Requires-Dist: pytest-watch>=4.2.0; extra == "dev"
Requires-Dist: black>=23.0.0; extra == "dev"
Requires-Dist: flake8>=6.1.0; extra == "dev"
Dynamic: license-file
Dynamic: requires-python
